dice_game.v
module dice_game (
    input rb,
    input reset,
    input clk,
    input [3:0] sum, 
    output reg roll,
    output reg win,
    output reg lose
);

    // State declarations
    reg [2:0] state, nextstate;
    reg [3:0] point;
    reg sp;

    parameter WAIT = 3'b000;
    parameter FIRST_ROLL = 3'b001;
    parameter WIN_STATE = 3'b010;
    parameter LOSE_STATE = 3'b011;
    parameter ROLL_AGAIN = 3'b100;

    always @(posedge clk or posedge reset) begin
        if (reset) begin
            state <= WAIT;
        end else begin
            state <= nextstate;
        end
    end

    always @(rb or reset or sum or state) begin
        // Default outputs
        sp <= 1'b0;
        roll <= 1'b0;
        win <= 1'b0;
        lose <= 1'b0;

        case (state)
            WAIT: begin
                if (rb) begin
                    nextstate <= FIRST_ROLL;
                end 
                else begin
                    nextstate <= WAIT;
                end
            end
            FIRST_ROLL: begin
                if (rb) begin
                    roll <= 1'b1;
                end 
                else if (sum == 7 || sum == 11) begin
                    nextstate <= WIN_STATE;
                end 
                else if (sum == 2 || sum == 3 || sum == 12) begin
                    nextstate <= LOSE_STATE;
                end 
                else begin
                    sp <= 1'b1;
                    nextstate <= ROLL_AGAIN;
                end
            end
            WIN_STATE: begin
                win <= 1'b1;
                if (reset) begin
                    nextstate <= WAIT;
                end
            end
            LOSE_STATE: begin
                lose <= 1'b1;
                if (reset) begin
                    nextstate <= WAIT;
                end
            end
            ROLL_AGAIN: begin
                if (rb) begin
                    roll <= 1'b1;
                
                    if (sum == point) begin
                        nextstate <= WIN_STATE;
                    end 
                    else if (sum == 7) begin
                        nextstate <= LOSE_STATE;
                    end 
                    else begin
                        nextstate <= ROLL_AGAIN;
                    end
                end
            end
        endcase
    end

    always @(posedge clk) begin
        if (sp) begin
            point <= sum;
        end
    end

endmodule

dice_game_tb.v
`timescale 1ns/1ps
`include "dice_game.v"
module dice_game_tb;

    reg rb;
    reg reset;
    reg clk;
    reg [3:0] sum;
    wire roll;
    wire win;
    wire lose;

    dice_game uut (
        .rb(rb),
        .reset(reset),
        .clk(clk),
        .sum(sum),
        .roll(roll),
        .win(win),
        .lose(lose)
    );

    always #5 clk = ~clk;

    initial begin
        $monitor("At time %t: rb = %b, reset = %b, clk = %b, sum = %d, roll = %b, win = %b, lose = %b",$time, rb, reset, clk, sum, roll, win, lose);

        //Initialize
        clk = 0;
        rb = 0;
        reset = 1;
        sum = 4'd0;

        #10 reset = 0;

        //Case 1
        #10 rb = 1;
        #10 rb = 0; sum = 4'd7; //win

        #10 reset=1;
        #10 reset=0;

        //case 2
        #20 rb = 1;
        #10 rb = 0; sum = 4'd3; //lose

        #10 reset=1;
        #10 reset=0;

        // Test case 3
        #20 rb = 1;
        #10 rb = 0; sum = 4'd4; //go to ROLL_AGAIN state
        #20 rb = 1;
        #10 rb = 0; sum = 4'd4; //win

        #10 reset=1;
        #10 reset=0;

        // Test case 4
        #20 rb = 1;
        #10 rb = 0; sum = 4'd12; //go to ROLL_AGAIN state
        #20 rb = 1;
        #10 rb = 0; sum = 4'd7; //lose

        #20 $finish;
    end

    initial begin
        $dumpfile("dice_game.vcd");
        $dumpvars(0, dice_game_tb);
    end
endmodule

dice_game.vcd
$date
	Thu Aug 08 18:23:13 2024
$end
$version
	Icarus Verilog
$end
$timescale
	1ps
$end
$scope module dice_game_tb $end
$var wire 1 ! win $end
$var wire 1 " roll $end
$var wire 1 # lose $end
$var reg 1 $ clk $end
$var reg 1 % rb $end
$var reg 1 & reset $end
$var reg 4 ' sum [3:0] $end
$scope module uut $end
$var wire 1 $ clk $end
$var wire 1 % rb $end
$var wire 1 & reset $end
$var wire 4 ( sum [3:0] $end
$var parameter 3 ) FIRST_ROLL $end
$var parameter 3 * LOSE_STATE $end
$var parameter 3 + ROLL_AGAIN $end
$var parameter 3 , WAIT $end
$var parameter 3 - WIN_STATE $end
$var reg 1 # lose $end
$var reg 3 . nextstate [2:0] $end
$var reg 4 / point [3:0] $end
$var reg 1 " roll $end
$var reg 1 0 sp $end
$var reg 3 1 state [2:0] $end
$var reg 1 ! win $end
$upscope $end
$upscope $end
$enddefinitions $end
$comment Show the parameter values. $end
$dumpall
b10 -
b0 ,
b100 +
b11 *
b1 )
$end
#0
$dumpvars
b0 1
00
bx /
b0 .
b0 (
b0 '
1&
0%
0$
0#
0"
0!
$end
#5000
1$
#10000
0$
0&
#15000
1$
#20000
b1 .
0$
1%
#25000
1"
b1 1
1$
#30000
b10 .
0"
0$
b111 '
b111 (
0%
#35000
1!
b10 1
1$
#40000
b0 .
0!
b0 1
0$
1&
#45000
1$
#50000
0$
0&
#55000
1$
#60000
0$
#65000
1$
#70000
b1 .
0$
1%
#75000
1"
b1 1
1$
#80000
b11 .
0"
0$
b11 '
b11 (
0%
#85000
1#
b11 1
1$
#90000
b0 .
0#
b0 1
0$
1&
#95000
1$
#100000
0$
0&
#105000
1$
#110000
0$
#115000
1$
#120000
b1 .
0$
1%
#125000
1"
b1 1
1$
#130000
b100 .
10
0"
0$
b100 '
b100 (
0%
#135000
00
b100 /
b100 1
1$
#140000
0$
#145000
1$
#150000
b10 .
1"
0$
1%
#155000
1!
0"
b10 1
1$
#160000
1!
0$
0%
#165000
1$
#170000
b0 .
0!
b0 1
0$
1&
#175000
1$
#180000
0$
0&
#185000
1$
#190000
0$
#195000
1$
#200000
b1 .
0$
1%
#205000
1"
b1 1
1$
#210000
b11 .
0"
0$
b1100 '
b1100 (
0%
#215000
1#
b11 1
1$
#220000
0$
#225000
1$
#230000
1#
0$
1%
#235000
1$
#240000
1#
0$
b111 '
b111 (
0%
